envjoy/__init__.py
envjoy/__init__.pyc
envjoy/env.py
envjoy/env.pyc
envjoy/tests/__init__.py
envjoy/tests/__main__.py
envjoy/tests/helper.py
envjoy/tests/test_env.py
envjoy-0.1.0.dist-info/METADATA
envjoy-0.1.0.dist-info/WHEEL
envjoy-0.1.0.dist-info/top_level.txt
envjoy-0.1.0.dist-info/zip-safe
envjoy-0.1.0.dist-info/RECORD
