Metadata-Version: 2.1
Name: envjoy
Version: 0.1.0
Summary: A more enjoyable environment variable getter and setter - for Python.
Home-page: https://github.com/grimen/python-envjoy
Author: Jonas Grimfelt
Author-email: grimen@gmail.com
License: MIT
Download-URL: https://github.com/grimen/python-envjoy
Project-URL: repository, https://github.com/grimen/python-envjoy
Project-URL: bugs, https://github.com/grimen/python-envjoy/issues
Keywords: env,environment,environ,variable,getter,setter,parser,caster,key,value
Platform: UNKNOWN
Classifier: Topic :: Software Development :: Libraries
Classifier: Development Status :: 5 - Production/Stable
Classifier: Intended Audience :: Developers
Classifier: License :: OSI Approved :: MIT License
Classifier: Operating System :: POSIX
Classifier: Programming Language :: Python
Classifier: Programming Language :: Python :: 2
Classifier: Programming Language :: Python :: 3
Classifier: Programming Language :: Python :: Implementation :: CPython
Classifier: Programming Language :: Python :: Implementation :: PyPy
Requires-Dist: six (>=1.11.0)
Requires-Dist: rootpath (>=0.1.0)
Requires-Dist: inspecta (>=0.1.0)
Requires-Dist: mybad (>=0.1.0)
Requires-Dist: colour-runner (>=0.0.5)
Requires-Dist: deepdiff (>=3.3.0)
Requires-Dist: tox (>=3.0.0)
